{"api_vite.md":"49a8cf2e","api_lifecycle.md":"4f67290b","api_cli.md":"85ae687b","blog_goal.md":"b1b4b6d4","guide_reform_extend.md":"0be86d81","blog_question-from.md":"9b11773e","guide_mode.md":"b435b6eb","guide_main.md":"7afd307c","blog_start.md":"a3193f88","question.md":"68c1bf5b","guide_react.md":"50bbc5dc","guide_reform_index.md":"a93e9fb6","blog_core.md":"540aae5b","api_vue.md":"73b41bb7","guide_sandbox.md":"805004fd","api_helper.md":"b29b65d2","guide_secondary_nest.md":"395efe8f","guide_secondary_perf.md":"6638fe0c","guide_vue.md":"a46256a5","blog_question.md":"57da7e1a","guide_secondary_loader.md":"4b472d2f","blog_action.md":"3f303843","api_webpack.md":"6092242e","guide_secondary_hmr.md":"2f9ae82f","blog_genre.md":"77213576","guide_quick-start.md":"64ea2637","index.md":"13cc83a2","api_main.md":"143f3851","guide_reform_proxy.md":"13e3e4d3","api_react.md":"3b256e52","guide_deactive.md":"f44f9229","guide_base.md":"1538fef6","blog_compare.md":"e9352e83","guide_secondary_debug.md":"e7314ce3","guide_lifecycle.md":"b2814b97","guide_index.md":"efb9e540"}
